{
  "receipt_id": "gamp5-self-review-loop-2026-05-02",
  "oq_signoff_commit": "c06afe11",
  "timestamp_utc": "2026-05-02T23:04:00Z",
  "gates": {
    "OQ-SR-001": "PASS",
    "OQ-SR-002": "PASS",
    "OQ-SR-003": "PASS",
    "OQ-SR-004": "PASS",
    "OQ-SR-005": "PASS",
    "MQ-SR-001": "PASS",
    "MQ-SR-002": "PASS",
    "MQ-SR-003": "PASS",
    "MQ-SR-004": "PASS",
    "MQ-SR-005": "PASS",
    "swift_tests_3x": "PASS",
    "GaiaFusion_3x": "PASS",
    "GaiaRTMGate": "CALORIE",
    "release_grep": "CLEAN"
  }
}
